stockholm_library/__init__.py
stockholm_library/client.py
stockholm_library/models/__init__.py
stockholm_library/models/book.py
stockholm_library/models/loan.py
stockholm_library/parsers/__init__.py
stockholm_library/parsers/loan_parser.py
stockholm_library-0.2.0.dist-info/LICENSE
stockholm_library-0.2.0.dist-info/METADATA
stockholm_library-0.2.0.dist-info/WHEEL
stockholm_library-0.2.0.dist-info/top_level.txt
stockholm_library-0.2.0.dist-info/RECORD
