Metadata-Version: 2.1
Name: stockholm-library
Version: 0.2.0
Summary: Unofficial SDK for interacting with Stockholm Library.
Home-page: https://github.com/vonNiklasson/stockholm-library-client
Author: Johan Niklasson
Author-email: johan@niklasson.me
License: MIT
Project-URL: Source, https://github.com/vonNiklasson/stockholm-library-client
Project-URL: Bug Reports, https://github.com/vonNiklasson/stockholm-library-client/issues
Keywords: Stockholm Library API
Platform: UNKNOWN
Classifier: Development Status :: 3 - Alpha
Classifier: License :: OSI Approved :: MIT License
Classifier: Intended Audience :: Developers
Classifier: Operating System :: OS Independent
Classifier: Programming Language :: Python :: 3
Classifier: Programming Language :: Python :: 3.6
Classifier: Programming Language :: Python :: 3.7
Classifier: Programming Language :: Python :: 3.8
Classifier: Programming Language :: Python :: 3.9
Classifier: Programming Language :: Python :: 3 :: Only
Classifier: Topic :: Software Development
Classifier: Topic :: Office/Business :: Financial :: Accounting
Requires-Python: >=3.6
License-File: LICENSE
Requires-Dist: requests[security] (<3,>=2)
Requires-Dist: beautifulsoup4 (<5,>=4)
